invenio_circulation/__init__.py
invenio_circulation/api.py
invenio_circulation/config.py
invenio_circulation/errors.py
invenio_circulation/ext.py
invenio_circulation/links.py
invenio_circulation/permissions.py
invenio_circulation/proxies.py
invenio_circulation/signals.py
invenio_circulation/utils.py
invenio_circulation/views.py
invenio_circulation/mappings/__init__.py
invenio_circulation/mappings/os-v1/__init__.py
invenio_circulation/mappings/os-v1/loans/loan-v1.0.0.json
invenio_circulation/mappings/os-v2/__init__.py
invenio_circulation/mappings/os-v2/loans/loan-v1.0.0.json
invenio_circulation/mappings/v7/__init__.py
invenio_circulation/mappings/v7/loans/loan-v1.0.0.json
invenio_circulation/pidstore/__init__.py
invenio_circulation/pidstore/fetchers.py
invenio_circulation/pidstore/minters.py
invenio_circulation/pidstore/pids.py
invenio_circulation/pidstore/providers.py
invenio_circulation/records/__init__.py
invenio_circulation/records/jsonresolver/__init__.py
invenio_circulation/records/jsonresolver/document.py
invenio_circulation/records/jsonresolver/item.py
invenio_circulation/records/jsonresolver/patron.py
invenio_circulation/records/loaders/__init__.py
invenio_circulation/records/loaders/schemas/__init__.py
invenio_circulation/records/loaders/schemas/json.py
invenio_circulation/schemas/__init__.py
invenio_circulation/schemas/loans/loan-v1.0.0.json
invenio_circulation/search/__init__.py
invenio_circulation/search/api.py
invenio_circulation/transitions/__init__.py
invenio_circulation/transitions/base.py
invenio_circulation/transitions/transitions.py
tests/__init__.py
tests/conftest.py
tests/helpers.py
tests/test_api_loan_status_item_pid.py
tests/test_circulation_state_machine.py
tests/test_errors.py
tests/test_invenio_circulation.py
tests/test_loan_base_constraints.py
tests/test_loan_record.py
tests/test_loan_search.py
tests/test_loan_transition_created_to_pending.py
tests/test_loan_transition_item_on_loan_to_item_returned.py
invenio_circulation-3.0.0a1.dist-info/AUTHORS.rst
invenio_circulation-3.0.0a1.dist-info/LICENSE
invenio_circulation-3.0.0a1.dist-info/METADATA
invenio_circulation-3.0.0a1.dist-info/WHEEL
invenio_circulation-3.0.0a1.dist-info/entry_points.txt
invenio_circulation-3.0.0a1.dist-info/top_level.txt
invenio_circulation-3.0.0a1.dist-info/RECORD
