Metadata-Version: 2.1
Name: invenio-circulation
Version: 3.0.0a1
Summary: Invenio Circulation Module
Home-page: https://github.com/inveniosoftware/invenio-circulation
Author: CERN
Author-email: info@inveniosoftware.org
License: MIT
Keywords: invenio-circulation Invenio
Platform: any
Classifier: Development Status :: 4 - Beta
Requires-Python: >=3.8
Requires-Dist: Babel >=2.8
Requires-Dist: arrow >=0.15.0
Requires-Dist: invenio-base >=1.2.4
Requires-Dist: invenio-access >=2.0.0
Requires-Dist: invenio-indexer >=2.0.0
Requires-Dist: invenio-logging >=2.0.0
Requires-Dist: invenio-pidstore >=1.3.0
Requires-Dist: invenio-records-rest >=2.2.0
Requires-Dist: invenio-jsonschemas >=1.1.4
Requires-Dist: jsonschema >=3.0.0
Provides-Extra: docs
Provides-Extra: elasticsearch7
Requires-Dist: invenio-search[elasticsearch7] <3.0.0,>=2.0.0 ; extra == 'elasticsearch7'
Requires-Dist: elasticsearch <7.14,>=7.0.0 ; extra == 'elasticsearch7'
Provides-Extra: mysql
Requires-Dist: invenio-db[mysql,versioning] <2.0.0,>=1.0.0 ; extra == 'mysql'
Provides-Extra: opensearch2
Requires-Dist: invenio-search[opensearch2] <3.0.0,>=2.0.0 ; extra == 'opensearch2'
Provides-Extra: postgresql
Requires-Dist: invenio-db[postgresql,versioning] <2.0.0,>=1.0.0 ; extra == 'postgresql'
Provides-Extra: sqlite
Requires-Dist: invenio-db[versioning] <2.0.0,>=1.0.0 ; extra == 'sqlite'
Provides-Extra: tests
Requires-Dist: mock >=2.0.0 ; extra == 'tests'
Requires-Dist: pytest-black >=0.3.0 ; extra == 'tests'
Requires-Dist: pytest-invenio <3.0.0,>=2.1.0 ; extra == 'tests'
Requires-Dist: pytest-mock >=1.6.0 ; extra == 'tests'
Requires-Dist: celery[pytest] <5.3,>=4.4.0 ; extra == 'tests'
Requires-Dist: invenio-app >=1.3.1 ; extra == 'tests'
Requires-Dist: invenio-jsonschemas >=1.0.1 ; extra == 'tests'
Requires-Dist: Flask <2.3.0,>=2.2.0 ; extra == 'tests'
Requires-Dist: pydocstyle ==6.1.1 ; extra == 'tests'
Requires-Dist: sphinx >=5 ; extra == 'tests'
